carbgremover/__init__.py
carbgremover/external_model.py
carbgremover/internal_model.py
carsegmentation-1.0.0.dist-info/METADATA
carsegmentation-1.0.0.dist-info/WHEEL
carsegmentation-1.0.0.dist-info/top_level.txt
carsegmentation-1.0.0.dist-info/RECORD
